{
  "task_name": "web_app_gather_headers",
  "entity": {
    "type": "WebApplication",
    "attributes": {
      "name": "http://acs.org"
    }
  },
  "entities": [
    {
      "type": "WebApplicationHeader",
      "attributes": {
        "name": "x-amz-id-2",
        "content": "8tldRu0l1VVj4PH+9OrcftWbxYS85WMHQcQ2FVIsync/mz73e2yIZLbCqd3x71z9c+9ns4Ym0+4="
      }
    },
    {
      "type": "WebApplicationHeader",
      "attributes": {
        "name": "x-amz-request-id",
        "content": "537946FAB9437881"
      }
    },
    {
      "type": "WebApplicationHeader",
      "attributes": {
        "name": "last-modified",
        "content": "Mon, 03 Feb 2014 16:22:19 GMT"
      }
    },
    {
      "type": "WebApplicationHeader",
      "attributes": {
        "name": "etag",
        "content": "\"444e2f7afa44b1330541b95d937c102f\""
      }
    },
    {
      "type": "WebApplicationHeader",
      "attributes": {
        "name": "content-type",
        "content": "text/html"
      }
    },
    {
      "type": "WebApplicationHeader",
      "attributes": {
        "name": "server",
        "content": "AmazonS3"
      }
    }
  ]
}