{
  "task_name": "web_app_gather_headers",
  "entity": {
    "type": "WebApplication",
    "attributes": {
      "name": "http://alwakeelnews.com"
    }
  },
  "entities": [
    {
      "type": "WebApplicationHeader",
      "attributes": {
        "name": "server",
        "content": "nginx"
      }
    },
    {
      "type": "WebApplicationHeader",
      "attributes": {
        "name": "content-type",
        "content": "text/html"
      }
    },
    {
      "type": "WebApplicationHeader",
      "attributes": {
        "name": "transfer-encoding",
        "content": "chunked"
      }
    },
    {
      "type": "WebApplicationHeader",
      "attributes": {
        "name": "connection",
        "content": "keep-alive"
      }
    },
    {
      "type": "WebApplicationHeader",
      "attributes": {
        "name": "set-cookie",
        "content": "PHPSESSID=bd6ced90f3e59d0df018fd7bbbe964af; path=/; domain=.alwakeelnews.com, tcid=1422010755710.8Lq50UfUCpPfS4DRnDqUvPdN9Bn.mSC; expires=Fri, 22-Jan-2016 10:59:15 GMT, mobile_co=on"
      }
    }
  ]
}