{
  "task_name": "web_app_gather_headers",
  "entity": {
    "type": "WebApplication",
    "attributes": {
      "name": "http://bikroy.com"
    }
  },
  "entities": [
    {
      "type": "WebApplicationHeader",
      "attributes": {
        "name": "content-type",
        "content": "text/html; charset=utf-8"
      }
    },
    {
      "type": "WebApplicationHeader",
      "attributes": {
        "name": "transfer-encoding",
        "content": "chunked"
      }
    },
    {
      "type": "WebApplicationHeader",
      "attributes": {
        "name": "connection",
        "content": "keep-alive"
      }
    },
    {
      "type": "WebApplicationHeader",
      "attributes": {
        "name": "set-cookie",
        "content": "__cfduid=d37ef1355192f78bb7cdac2bfef37e7261422090252; expires=Sun, 24-Jan-16 09:04:12 GMT; path=/; domain=.bikroy.com; HttpOnly, locale=bn; domain=.bikroy.com; path=/, _first_visit=yes; path=/, _cookie_id=qtLsoXcH74YSVsx9vQBJqQVm1W1GGXVkk9SxsFptDEfQAuAE3w3aqr2dqK2vpd6g; path=/; expires=Wed, 24-Jan-2035 09:04:13 GMT, _session_id=6e762bbfe1bd2ad3832cc5f74630af66; path=/; expires=Sat, 24-Jan-2015 13:04:13 GMT; HttpOnly, user=; path=/; expires=Thu, 01-Jan-1970 00:00:00 GMT"
      }
    },
    {
      "type": "WebApplicationHeader",
      "attributes": {
        "name": "access-control-allow-origin",
        "content": "*"
      }
    },
    {
      "type": "WebApplicationHeader",
      "attributes": {
        "name": "access-control-expose-headers",
        "content": "X-Request-Id, X-Runtime, X-Rack-Cache"
      }
    },
    {
      "type": "WebApplicationHeader",
      "attributes": {
        "name": "cache-control",
        "content": "max-age=3600, private"
      }
    },
    {
      "type": "WebApplicationHeader",
      "attributes": {
        "name": "status",
        "content": "200 OK"
      }
    },
    {
      "type": "WebApplicationHeader",
      "attributes": {
        "name": "vary",
        "content": "Accept-Encoding, Cookie, User-Agent"
      }
    },
    {
      "type": "WebApplicationHeader",
      "attributes": {
        "name": "x-rack-cache",
        "content": "miss"
      }
    },
    {
      "type": "WebApplicationHeader",
      "attributes": {
        "name": "x-request-id",
        "content": "10892be9b303687a9b59713f5d8e68da"
      }
    },
    {
      "type": "WebApplicationHeader",
      "attributes": {
        "name": "x-runtime",
        "content": "0.626205"
      }
    },
    {
      "type": "WebApplicationHeader",
      "attributes": {
        "name": "x-trace",
        "content": "1B9BCA3286622CD868B79C6F1B1F7A84976AA62BD6FE10E9FDB46021F8"
      }
    },
    {
      "type": "WebApplicationHeader",
      "attributes": {
        "name": "x-ua-compatible",
        "content": "IE=Edge,chrome=1"
      }
    },
    {
      "type": "WebApplicationHeader",
      "attributes": {
        "name": "server",
        "content": "cloudflare-nginx"
      }
    },
    {
      "type": "WebApplicationHeader",
      "attributes": {
        "name": "cf-ray",
        "content": "1adb0fef1356016a-ORD"
      }
    }
  ]
}