{
  "task_name": "web_app_gather_headers",
  "entity": {
    "type": "WebApplication",
    "attributes": {
      "name": "http://bonanza.com"
    }
  },
  "entities": [
    {
      "type": "WebApplicationHeader",
      "attributes": {
        "name": "server",
        "content": "Apache/2.2.22 (Ubuntu)"
      }
    },
    {
      "type": "WebApplicationHeader",
      "attributes": {
        "name": "content-language",
        "content": "en-US"
      }
    },
    {
      "type": "WebApplicationHeader",
      "attributes": {
        "name": "x-ua-compatible",
        "content": "IE=Edge,chrome=1"
      }
    },
    {
      "type": "WebApplicationHeader",
      "attributes": {
        "name": "etag",
        "content": "\"05dc6875150936a0dfbc444efe89b2c1\""
      }
    },
    {
      "type": "WebApplicationHeader",
      "attributes": {
        "name": "cache-control",
        "content": "max-age=0, private, must-revalidate"
      }
    },
    {
      "type": "WebApplicationHeader",
      "attributes": {
        "name": "x-request-id",
        "content": "62748ec65d23a619418bcf6eab80ed4b"
      }
    },
    {
      "type": "WebApplicationHeader",
      "attributes": {
        "name": "x-runtime",
        "content": "0.167355"
      }
    },
    {
      "type": "WebApplicationHeader",
      "attributes": {
        "name": "x-rack-cache",
        "content": "miss"
      }
    },
    {
      "type": "WebApplicationHeader",
      "attributes": {
        "name": "x-powered-by",
        "content": "Phusion Passenger 4.0.53"
      }
    },
    {
      "type": "WebApplicationHeader",
      "attributes": {
        "name": "set-cookie",
        "content": "locale=en-US; domain=.bonanza.com; path=/; expires=Sun, 18-Jan-2015 05:28:56 GMT, intrkrf=Direct; domain=.bonanza.com; path=/, intrkep=http%3A%2F%2Fwww.bonanza.com%2F; domain=.bonanza.com; path=/, intrkvc=1; domain=.bonanza.com; path=/, source_em=4; path=/, intrkld=1421472536.150054; domain=.bonanza.com; path=/, pxa=jAukDmwoWlFG7qJnsgUc5TNY4; path=/, _session_id=8efe6ef94b948a6468dff2817e2b8a1a; domain=.bonanza.com; path=/"
      }
    },
    {
      "type": "WebApplicationHeader",
      "attributes": {
        "name": "status",
        "content": "200 OK"
      }
    },
    {
      "type": "WebApplicationHeader",
      "attributes": {
        "name": "vary",
        "content": "Accept-Encoding"
      }
    },
    {
      "type": "WebApplicationHeader",
      "attributes": {
        "name": "content-type",
        "content": "text/html; charset=utf-8"
      }
    },
    {
      "type": "WebApplicationHeader",
      "attributes": {
        "name": "x-frontend",
        "content": "http"
      }
    }
  ]
}