{
  "task_name": "web_app_gather_headers",
  "entity": {
    "type": "WebApplication",
    "attributes": {
      "name": "http://cars.com"
    }
  },
  "entities": [
    {
      "type": "WebApplicationHeader",
      "attributes": {
        "name": "x-powered-by",
        "content": "Servlet/3.0"
      }
    },
    {
      "type": "WebApplicationHeader",
      "attributes": {
        "name": "x-dynatrace-js-agent",
        "content": "true"
      }
    },
    {
      "type": "WebApplicationHeader",
      "attributes": {
        "name": "set-cookie",
        "content": "dtCookie=F40938A61B80D16E14637E85E4FBCA7E|_default|1; Path=/; Domain=.cars.com, JSESSIONID=0000IGsLm-xqLkPyorVwPUQVsC2:1821leu9i; Path=/; HttpOnly, Registration=currentUserId:fiU7zdj6aaHWk5Zioo8yKbtGFQMgZeQuu0YVAyBl5C67RhUDIGXkLrtGFQMgZeQuEvOD/VRoptryOYYMuxRWiRs056hBXLs84Hye47Z6DyE=; Expires=Tue, 14-Jan-20 12:16:16 GMT; Path=/; Domain=www.cars.com, affiliate=national; Expires=Thu, 05-Feb-15 12:16:16 GMT; Path=/; Domain=www.cars.com, cars_persist=2655065260.20480.0000; expires=Thu, 15-Jan-2015 12:46:16 GMT; path=/, TS01952cdc=01fce1e7c49d1d0fbe4e877da6989a067ad8d3a10deea60a6cad31e4c228a989db82a155117b20b37e49e983aa8f09f0285245a23be373b5b562b75d2a444a5af3b0ee8fb2; Path=/, TS011184a0=01fce1e7c43a09f711c8aedb1546e08bfe65f6f010f8fc750ec2bc0886fc710ff4fb14db6f6725266eda3d53e0d52704f66cf8f582; path=/; domain=.cars.com, TS01eea597=01fce1e7c44cdb628d50b52cdd2848d95984ee2eb9df46e84bec0320691db7923f75b7c0bd40146315a331e8b494b783b99ec3747e9ea8fb166a2087d48fe190d9922de1d4; path=/; domain=www.cars.com"
      }
    },
    {
      "type": "WebApplicationHeader",
      "attributes": {
        "name": "cache-control",
        "content": "no-cache=\"set-cookie, set-cookie2\""
      }
    },
    {
      "type": "WebApplicationHeader",
      "attributes": {
        "name": "p3p",
        "content": "policyref=\"/w3c/p3p.xml\", CP=\"ALL DEM ONL PHY PUR CUR OUR BUS IND\""
      }
    },
    {
      "type": "WebApplicationHeader",
      "attributes": {
        "name": "content-type",
        "content": "text/html;charset=ISO-8859-1"
      }
    },
    {
      "type": "WebApplicationHeader",
      "attributes": {
        "name": "content-language",
        "content": "en-US"
      }
    },
    {
      "type": "WebApplicationHeader",
      "attributes": {
        "name": "vary",
        "content": "Accept-Encoding"
      }
    },
    {
      "type": "WebApplicationHeader",
      "attributes": {
        "name": "transfer-encoding",
        "content": "chunked"
      }
    }
  ]
}