{
  "task_name": "web_app_gather_headers",
  "entity": {
    "type": "WebApplication",
    "attributes": {
      "name": "http://dealcatcher.com"
    }
  },
  "entities": [
    {
      "type": "WebApplicationHeader",
      "attributes": {
        "name": "content-type",
        "content": "text/html"
      }
    },
    {
      "type": "WebApplicationHeader",
      "attributes": {
        "name": "transfer-encoding",
        "content": "chunked"
      }
    },
    {
      "type": "WebApplicationHeader",
      "attributes": {
        "name": "connection",
        "content": "keep-alive"
      }
    },
    {
      "type": "WebApplicationHeader",
      "attributes": {
        "name": "set-cookie",
        "content": "__cfduid=dd7a354f3675619e5152b6ea5f9d4ca1f1424965508; expires=Fri, 26-Feb-16 15:45:08 GMT; path=/; domain=.dealcatcher.com; HttpOnly"
      }
    },
    {
      "type": "WebApplicationHeader",
      "attributes": {
        "name": "vary",
        "content": "Accept-Encoding"
      }
    },
    {
      "type": "WebApplicationHeader",
      "attributes": {
        "name": "etag",
        "content": "W/\"22750-54ef3f82-469be7\""
      }
    },
    {
      "type": "WebApplicationHeader",
      "attributes": {
        "name": "last-modified",
        "content": "Thu, 26 Feb 2015 15:45:06 GMT"
      }
    },
    {
      "type": "WebApplicationHeader",
      "attributes": {
        "name": "server",
        "content": "cloudflare-nginx"
      }
    },
    {
      "type": "WebApplicationHeader",
      "attributes": {
        "name": "cf-ray",
        "content": "1bed449b10db1177-DFW"
      }
    }
  ]
}