{
  "task_name": "web_app_gather_headers",
  "entity": {
    "type": "WebApplication",
    "attributes": {
      "name": "http://honto.jp"
    }
  },
  "entities": [
    {
      "type": "WebApplicationHeader",
      "attributes": {
        "name": "server",
        "content": "Apache"
      }
    },
    {
      "type": "WebApplicationHeader",
      "attributes": {
        "name": "x-publis-status",
        "content": "REDIRECT TO PublisRedirectUri"
      }
    },
    {
      "type": "WebApplicationHeader",
      "attributes": {
        "name": "cache-control",
        "content": "no-store, no-cache, must-revalidate, post-check=0, pre-check=0"
      }
    },
    {
      "type": "WebApplicationHeader",
      "attributes": {
        "name": "pragma",
        "content": "no-cache"
      }
    },
    {
      "type": "WebApplicationHeader",
      "attributes": {
        "name": "content-type",
        "content": "text/html; charset=UTF-8"
      }
    },
    {
      "type": "WebApplicationHeader",
      "attributes": {
        "name": "set-cookie",
        "content": "HBSSESSID=p9uidt2icfbcucl1kd4j98uik6; path=/; HttpOnly, psid=87528a688a2c430d63c9841bd7114c2e1421819410; expires=Tue, 21-Apr-2015 05:50:10 GMT; path=/; httponly, trid=5c65001c-a131-11e4-8db7-b16c37320f46.0; expires=Sat, 03-Jan-2026 05:50:10 GMT; path=/; httponly, scid=5c65001c-a131-11e4-8db7-b16c37320f46.0; expires=Sat, 03-Jan-2026 05:50:10 GMT; path=/; httponly"
      }
    },
    {
      "type": "WebApplicationHeader",
      "attributes": {
        "name": "vary",
        "content": "Accept-Encoding,User-Agent"
      }
    },
    {
      "type": "WebApplicationHeader",
      "attributes": {
        "name": "transfer-encoding",
        "content": "chunked"
      }
    }
  ]
}