{
  "task_name": "web_app_gather_headers",
  "entity": {
    "type": "WebApplication",
    "attributes": {
      "name": "http://intuit.com"
    }
  },
  "entities": [
    {
      "type": "WebApplicationHeader",
      "attributes": {
        "name": "server",
        "content": "Apache"
      }
    },
    {
      "type": "WebApplicationHeader",
      "attributes": {
        "name": "x-showroom-hostname",
        "content": "pprddgtws30d.ie.intuit.net"
      }
    },
    {
      "type": "WebApplicationHeader",
      "attributes": {
        "name": "x-showroom-cms-preview-mode",
        "content": "off"
      }
    },
    {
      "type": "WebApplicationHeader",
      "attributes": {
        "name": "x-ua-compatible",
        "content": "IE=Edge,chrome=1"
      }
    },
    {
      "type": "WebApplicationHeader",
      "attributes": {
        "name": "etag",
        "content": "\"f477a77870875a77a276ecf6e621abe4\""
      }
    },
    {
      "type": "WebApplicationHeader",
      "attributes": {
        "name": "cache-control",
        "content": "max-age=0, private, must-revalidate"
      }
    },
    {
      "type": "WebApplicationHeader",
      "attributes": {
        "name": "x-request-id",
        "content": "677ba995b5767617ee91efdd106005ab"
      }
    },
    {
      "type": "WebApplicationHeader",
      "attributes": {
        "name": "x-runtime",
        "content": "0.263759"
      }
    },
    {
      "type": "WebApplicationHeader",
      "attributes": {
        "name": "x-rack-cache",
        "content": "miss"
      }
    },
    {
      "type": "WebApplicationHeader",
      "attributes": {
        "name": "status",
        "content": "200"
      }
    },
    {
      "type": "WebApplicationHeader",
      "attributes": {
        "name": "strict-transport-security",
        "content": "max-age=0"
      }
    },
    {
      "type": "WebApplicationHeader",
      "attributes": {
        "name": "vary",
        "content": "Accept-Encoding"
      }
    },
    {
      "type": "WebApplicationHeader",
      "attributes": {
        "name": "content-type",
        "content": "text/html; charset=utf-8"
      }
    },
    {
      "type": "WebApplicationHeader",
      "attributes": {
        "name": "set-cookie",
        "content": "_intuit_com_session=BAh7B0kiD3Nlc3Npb25faWQGOgZFRkkiJTI0YzZmMTIzMDAzOWU1NjI1NmUwZGE2YWU2ODA2NTdkBjsAVEkiEF9jc3JmX3Rva2VuBjsARkkiMXI4V25YSW9NNUI4Mml1d3VHQ3lURENUK2xIcmRDOTB1WEJzS3dtOVlyWTg9BjsARg%3D%3D--f8740fedfd58d2a5f6be567299b7c191a93df2d6; path=/; HttpOnly"
      }
    },
    {
      "type": "WebApplicationHeader",
      "attributes": {
        "name": "rtss",
        "content": "1-1-131"
      }
    }
  ]
}