{
  "task_name": "web_app_gather_headers",
  "entity": {
    "type": "WebApplication",
    "attributes": {
      "name": "http://linkedin.com"
    }
  },
  "entities": [
    {
      "type": "WebApplicationHeader",
      "attributes": {
        "name": "server",
        "content": "Apache-Coyote/1.1"
      }
    },
    {
      "type": "WebApplicationHeader",
      "attributes": {
        "name": "p3p",
        "content": "CP=\"CAO CUR ADM DEV PSA PSD OUR\""
      }
    },
    {
      "type": "WebApplicationHeader",
      "attributes": {
        "name": "x-frame-options",
        "content": "SAMEORIGIN"
      }
    },
    {
      "type": "WebApplicationHeader",
      "attributes": {
        "name": "vary",
        "content": "Accept-Encoding"
      }
    },
    {
      "type": "WebApplicationHeader",
      "attributes": {
        "name": "content-type",
        "content": "text/html;charset=UTF-8"
      }
    },
    {
      "type": "WebApplicationHeader",
      "attributes": {
        "name": "content-language",
        "content": "en-US"
      }
    },
    {
      "type": "WebApplicationHeader",
      "attributes": {
        "name": "x-fs-uuid",
        "content": "7fe06d360526ba13d0acb9fa3b2b0000"
      }
    },
    {
      "type": "WebApplicationHeader",
      "attributes": {
        "name": "x-page-speed",
        "content": "1"
      }
    },
    {
      "type": "WebApplicationHeader",
      "attributes": {
        "name": "x-content-type-options",
        "content": "nosniff"
      }
    },
    {
      "type": "WebApplicationHeader",
      "attributes": {
        "name": "x-xss-protection",
        "content": "1; mode=block"
      }
    },
    {
      "type": "WebApplicationHeader",
      "attributes": {
        "name": "x-li-fabric",
        "content": "PROD-ELA4"
      }
    },
    {
      "type": "WebApplicationHeader",
      "attributes": {
        "name": "strict-transport-security",
        "content": "max-age=0"
      }
    },
    {
      "type": "WebApplicationHeader",
      "attributes": {
        "name": "set-cookie",
        "content": "_lipt=deleteMe; Expires=Thu, 01-Jan-1970 00:00:10 GMT; Path=/, leo_auth_token=\"GST:ZKsp88Trhe3ZFnyQlaj58ZR-XYQgRFt0mAdhTMkrsvl_WfVTAmD5nD:1421490436:ba6d7f95e0f0cd50bb44a927ff0aa47ba85390f0\"; Version=1; Max-Age=1799; Expires=Sat, 17-Jan-2015 10:57:15 GMT; Path=/, sl=\"delete me\"; Version=1; Max-Age=0; Expires=Thu, 01-Jan-1970 00:00:10 GMT; Path=/, sl=\"delete me\"; Version=1; Domain=.www.linkedin.com; Max-Age=0; Expires=Thu, 01-Jan-1970 00:00:10 GMT; Path=/, s_leo_auth_token=\"delete me\"; Version=1; Max-Age=0; Expires=Thu, 01-Jan-1970 00:00:10 GMT; Path=/, JSESSIONID=\"ajax:5773809465128092925\"; Version=1; Domain=.www.linkedin.com; Path=/, visit=\"v=1&G\"; Version=1; Max-Age=63072000; Expires=Mon, 16-Jan-2017 10:27:16 GMT; Path=/, bcookie=\"v=2&7ea71dbd-edd9-49b5-8e11-6d5e4b252e2b\"; domain=.linkedin.com; Path=/; Expires=Mon, 16-Jan-2017 22:04:48 GMT, bscookie=\"v=1&2015011710271679947736-3089-4f14-805c-ae3d3076f72fAQGNiV4ZFZAkJGYliXO2M7U7HWoFaSfB\"; domain=.www.linkedin.com; Path=/; Secure; Expires=Mon, 16-Jan-2017 22:04:48 GMT; HttpOnly, lidc=\"b=LB11:g=166:u=1:i=1421490436:t=1421576836:s=3145689211\"; Expires=Sun, 18 Jan 2015 10:27:16 GMT; domain=.linkedin.com; Path=/"
      }
    },
    {
      "type": "WebApplicationHeader",
      "attributes": {
        "name": "pragma",
        "content": "no-cache"
      }
    },
    {
      "type": "WebApplicationHeader",
      "attributes": {
        "name": "cache-control",
        "content": "no-cache, no-store"
      }
    },
    {
      "type": "WebApplicationHeader",
      "attributes": {
        "name": "transfer-encoding",
        "content": "chunked"
      }
    },
    {
      "type": "WebApplicationHeader",
      "attributes": {
        "name": "connection",
        "content": "keep-alive"
      }
    },
    {
      "type": "WebApplicationHeader",
      "attributes": {
        "name": "x-li-pop",
        "content": "PROD-ELA4"
      }
    },
    {
      "type": "WebApplicationHeader",
      "attributes": {
        "name": "x-li-uuid",
        "content": "f+BtNgUmuhPQrLn6OysAAA=="
      }
    }
  ]
}