{
  "task_name": "web_app_gather_headers",
  "entity": {
    "type": "WebApplication",
    "attributes": {
      "name": "http://meh.com"
    }
  },
  "entities": [
    {
      "type": "WebApplicationHeader",
      "attributes": {
        "name": "transfer-encoding",
        "content": "chunked"
      }
    },
    {
      "type": "WebApplicationHeader",
      "attributes": {
        "name": "content-type",
        "content": "text/html; charset=utf-8"
      }
    },
    {
      "type": "WebApplicationHeader",
      "attributes": {
        "name": "etag",
        "content": "W/\"6V1QOWTb+rLOL62daZ2Hqg==\""
      }
    },
    {
      "type": "WebApplicationHeader",
      "attributes": {
        "name": "vary",
        "content": "Accept-Encoding"
      }
    },
    {
      "type": "WebApplicationHeader",
      "attributes": {
        "name": "server",
        "content": "Microsoft-IIS/8.5"
      }
    },
    {
      "type": "WebApplicationHeader",
      "attributes": {
        "name": "set-cookie",
        "content": "session.meh.com=s%3AQGivw9b9oLssueMSDtCLLeaszDUZGmdr.whiFkSjicwzrdWIG0poRz94LWz2K1LBXvjOmasxumYU; Path=/; Expires=Fri, 22 Jan 2016 13:44:07 GMT; HttpOnly; Secure"
      }
    },
    {
      "type": "WebApplicationHeader",
      "attributes": {
        "name": "x-powered-by",
        "content": "ASP.NET"
      }
    }
  ]
}