{
  "task_name": "web_app_gather_headers",
  "entity": {
    "type": "WebApplication",
    "attributes": {
      "name": "http://mxtoolbox.com"
    }
  },
  "entities": [
    {
      "type": "WebApplicationHeader",
      "attributes": {
        "name": "cache-control",
        "content": "private"
      }
    },
    {
      "type": "WebApplicationHeader",
      "attributes": {
        "name": "content-type",
        "content": "text/html; charset=utf-8"
      }
    },
    {
      "type": "WebApplicationHeader",
      "attributes": {
        "name": "vary",
        "content": "Accept-Encoding"
      }
    },
    {
      "type": "WebApplicationHeader",
      "attributes": {
        "name": "server",
        "content": "Microsoft-IIS/7.5"
      }
    },
    {
      "type": "WebApplicationHeader",
      "attributes": {
        "name": "x-powered-by",
        "content": "UrlRewriter.NET 2.0.0, ASP.NET"
      }
    },
    {
      "type": "WebApplicationHeader",
      "attributes": {
        "name": "set-cookie",
        "content": "ASP.NET_SessionId=s0u55a4nkcdhsoxerdt55o3x; path=/; HttpOnly, MxVisitorUID=69c6e17d-6890-4ad9-8d91-d28b618793d7; expires=Fri, 17-Jan-2020 15:34:45 GMT; path=/, ismobile=False; expires=Sun, 25-Jan-2015 15:34:45 GMT; path=/"
      }
    },
    {
      "type": "WebApplicationHeader",
      "attributes": {
        "name": "x-aspnet-version",
        "content": "4.0.30319"
      }
    },
    {
      "type": "WebApplicationHeader",
      "attributes": {
        "name": "access-control-allow-origin",
        "content": "*"
      }
    }
  ]
}