{
  "task_name": "web_app_gather_headers",
  "entity": {
    "type": "WebApplication",
    "attributes": {
      "name": "http://opencart.com"
    }
  },
  "entities": [
    {
      "type": "WebApplicationHeader",
      "attributes": {
        "name": "content-type",
        "content": "text/html; charset=UTF-8"
      }
    },
    {
      "type": "WebApplicationHeader",
      "attributes": {
        "name": "transfer-encoding",
        "content": "chunked"
      }
    },
    {
      "type": "WebApplicationHeader",
      "attributes": {
        "name": "connection",
        "content": "keep-alive"
      }
    },
    {
      "type": "WebApplicationHeader",
      "attributes": {
        "name": "set-cookie",
        "content": "__cfduid=d613a378732f662daf63b2e1dae001a7d1421577205; expires=Mon, 18-Jan-16 10:33:25 GMT; path=/; domain=.opencart.com; HttpOnly, PHPSESSID=3a10c42800b89b31dabcd7eeb31b8dd5; path=/, currency=USD; expires=Tue, 17-Feb-2015 10:33:24 GMT; path=/; domain=www.opencart.com"
      }
    },
    {
      "type": "WebApplicationHeader",
      "attributes": {
        "name": "x-powered-by",
        "content": "PHP/5.3.29"
      }
    },
    {
      "type": "WebApplicationHeader",
      "attributes": {
        "name": "cache-control",
        "content": "post-check=0, pre-check=0"
      }
    },
    {
      "type": "WebApplicationHeader",
      "attributes": {
        "name": "pragma",
        "content": "no-cache"
      }
    },
    {
      "type": "WebApplicationHeader",
      "attributes": {
        "name": "last-modified",
        "content": "Sun, 18 Jan 2015 10:33:24 GMT"
      }
    },
    {
      "type": "WebApplicationHeader",
      "attributes": {
        "name": "server",
        "content": "cloudflare-nginx"
      }
    },
    {
      "type": "WebApplicationHeader",
      "attributes": {
        "name": "cf-ray",
        "content": "1aaa225f377e1165-DFW"
      }
    }
  ]
}