{
  "task_name": "web_app_gather_headers",
  "entity": {
    "type": "WebApplication",
    "attributes": {
      "name": "http://pcgameshardware.de"
    }
  },
  "entities": [
    {
      "type": "WebApplicationHeader",
      "attributes": {
        "name": "server",
        "content": "Apache"
      }
    },
    {
      "type": "WebApplicationHeader",
      "attributes": {
        "name": "set-cookie",
        "content": "CFID=370957906;expires=Thu, 12-Jan-2045 11:47:48 GMT;path=/, CFTOKEN=c768f0a800a33be7-072B894E-DFC2-9218-C8C63ACA35D03C62;expires=Thu, 12-Jan-2045 11:47:48 GMT;path=/, CPTBP=2890072;domain=pcgameshardware.de;path=/"
      }
    },
    {
      "type": "WebApplicationHeader",
      "attributes": {
        "name": "x-ua-compatible",
        "content": "IE=edge"
      }
    },
    {
      "type": "WebApplicationHeader",
      "attributes": {
        "name": "cache-control",
        "content": "max-age=0"
      }
    },
    {
      "type": "WebApplicationHeader",
      "attributes": {
        "name": "vary",
        "content": "Accept-Encoding"
      }
    },
    {
      "type": "WebApplicationHeader",
      "attributes": {
        "name": "transfer-encoding",
        "content": "chunked"
      }
    },
    {
      "type": "WebApplicationHeader",
      "attributes": {
        "name": "content-type",
        "content": "text/html; charset=UTF-8"
      }
    }
  ]
}