{
  "task_name": "web_app_gather_headers",
  "entity": {
    "type": "WebApplication",
    "attributes": {
      "name": "http://prom.ua"
    }
  },
  "entities": [
    {
      "type": "WebApplicationHeader",
      "attributes": {
        "name": "server",
        "content": "nginx/1.7.7"
      }
    },
    {
      "type": "WebApplicationHeader",
      "attributes": {
        "name": "content-type",
        "content": "text/html; charset=utf-8"
      }
    },
    {
      "type": "WebApplicationHeader",
      "attributes": {
        "name": "transfer-encoding",
        "content": "chunked"
      }
    },
    {
      "type": "WebApplicationHeader",
      "attributes": {
        "name": "connection",
        "content": "keep-alive"
      }
    },
    {
      "type": "WebApplicationHeader",
      "attributes": {
        "name": "pragma",
        "content": "no-cache"
      }
    },
    {
      "type": "WebApplicationHeader",
      "attributes": {
        "name": "cache-control",
        "content": "no-cache"
      }
    },
    {
      "type": "WebApplicationHeader",
      "attributes": {
        "name": "set-cookie",
        "content": "user_tracker=8d655044762c4dd1ae5e6fe55c8bb9bf4e55ad6c|104.237.133.83|2015-01-19 15:39:19.202697; Domain=.prom.ua; Path=/, session_region_id=0; Domain=.prom.ua; Path=/, prom=069d2f9f7b4a0179c2abc3356563a8ce0716050a9d9747ac0c264188a245b6e914db7f00; Domain=.prom.ua; httponly; Path=/, csrf_token=a44fe147445a489f9329b4aef1e45838; Domain=.prom.ua; expires=\"Mon, 18-Jan-2016 13:39:19 GMT\"; Max-Age=31449600; Path=/, auth=0aba720f7abbe3fdd59c0c59b2f3003d02570479; Domain=.prom.ua; expires=\"Tue, 19-Jan-2016 13:39:19 GMT\"; httponly; Max-Age=31536000; Path=/"
      }
    }
  ]
}