{
  "task_name": "web_app_gather_headers",
  "entity": {
    "type": "WebApplication",
    "attributes": {
      "name": "http://raise.com"
    }
  },
  "entities": [
    {
      "type": "WebApplicationHeader",
      "attributes": {
        "name": "cache-control",
        "content": "max-age=0, private, must-revalidate"
      }
    },
    {
      "type": "WebApplicationHeader",
      "attributes": {
        "name": "content-type",
        "content": "text/html; charset=utf-8"
      }
    },
    {
      "type": "WebApplicationHeader",
      "attributes": {
        "name": "etag",
        "content": "\"b08b66ea1f4bcc426a3ed335d86748fb\""
      }
    },
    {
      "type": "WebApplicationHeader",
      "attributes": {
        "name": "server",
        "content": "nginx"
      }
    },
    {
      "type": "WebApplicationHeader",
      "attributes": {
        "name": "set-cookie",
        "content": "_coupontrade_browser_uid=49ee68f654873389f3f74b042a778d2273965665ddb8922e94a4818ee29a8742; path=/; expires=Thu, 25-Jan-2035 02:09:25 GMT; secure, _coupontrade_session_uid=827b5d7ebc063a7fb0fa62311805874ca2ca3e1646b3db6c60f9bb6b76d95459; path=/; expires=Sun, 25-Jan-2015 02:29:25 GMT; secure, _coupontrade_session=72ff82c3e25114dc4295337ed932e414; path=/; expires=Sun, 25-Jan-2015 02:29:25 GMT; secure; HttpOnly"
      }
    },
    {
      "type": "WebApplicationHeader",
      "attributes": {
        "name": "status",
        "content": "200 OK"
      }
    },
    {
      "type": "WebApplicationHeader",
      "attributes": {
        "name": "strict-transport-security",
        "content": "max-age=31536000"
      }
    },
    {
      "type": "WebApplicationHeader",
      "attributes": {
        "name": "vary",
        "content": "Accept-Encoding"
      }
    },
    {
      "type": "WebApplicationHeader",
      "attributes": {
        "name": "x-rack-cache",
        "content": "miss"
      }
    },
    {
      "type": "WebApplicationHeader",
      "attributes": {
        "name": "x-request-id",
        "content": "df49ecbf0c544f01da2fd020449cb033"
      }
    },
    {
      "type": "WebApplicationHeader",
      "attributes": {
        "name": "x-runtime",
        "content": "0.052878"
      }
    },
    {
      "type": "WebApplicationHeader",
      "attributes": {
        "name": "x-ua-compatible",
        "content": "IE=Edge,chrome=1"
      }
    },
    {
      "type": "WebApplicationHeader",
      "attributes": {
        "name": "connection",
        "content": "keep-alive"
      }
    }
  ]
}