{
  "task_name": "web_app_gather_headers",
  "entity": {
    "type": "WebApplication",
    "attributes": {
      "name": "http://register.com"
    }
  },
  "entities": [
    {
      "type": "WebApplicationHeader",
      "attributes": {
        "name": "set-cookie",
        "content": "TLTSID=DDD0B756A13910A1447FF7E69E531AD6; Path=/; Domain=.register.com, JSESSIONID=17C889E0CB5B422103DAA09335B3899E.janus-production; Path=/, R=rcomCookieTS&2015-01-21/01.51.03&trkid&WWW000000000W&; Expires=Wed, 25-Feb-2015 06:51:03 GMT; Path=/, JSESSIONID=17C889E0CB5B422103DAA09335B3899E.janus-production; Path=/, TSfd06f3=dac04686a9538faa7512f3411671fe6ce9d02b6405064fd254bf4c57286023f2c982646c60ac0ec5fae9336c16f670b9f47144a760ac0ec5fae9336c; Path=/"
      }
    },
    {
      "type": "WebApplicationHeader",
      "attributes": {
        "name": "hostname",
        "content": "atleuapp05.galt.register.com"
      }
    },
    {
      "type": "WebApplicationHeader",
      "attributes": {
        "name": "x-powered-by",
        "content": "Servlet 2.5; JBoss-5.0/JBossWeb-2.1"
      }
    },
    {
      "type": "WebApplicationHeader",
      "attributes": {
        "name": "cache-control",
        "content": "no-cache"
      }
    },
    {
      "type": "WebApplicationHeader",
      "attributes": {
        "name": "pragma",
        "content": "no-cache"
      }
    },
    {
      "type": "WebApplicationHeader",
      "attributes": {
        "name": "p3p",
        "content": "policyref=\"http://www.register.com/websitepolicy.xml\""
      }
    },
    {
      "type": "WebApplicationHeader",
      "attributes": {
        "name": "content-type",
        "content": "text/html;charset=ISO-8859-1"
      }
    },
    {
      "type": "WebApplicationHeader",
      "attributes": {
        "name": "vary",
        "content": "Accept-Encoding, User-Agent"
      }
    },
    {
      "type": "WebApplicationHeader",
      "attributes": {
        "name": "connection",
        "content": "Keep-Alive"
      }
    }
  ]
}