{
  "task_name": "web_app_gather_headers",
  "entity": {
    "type": "WebApplication",
    "attributes": {
      "name": "http://reverb.com"
    }
  },
  "entities": [
    {
      "type": "WebApplicationHeader",
      "attributes": {
        "name": "server",
        "content": "nginx"
      }
    },
    {
      "type": "WebApplicationHeader",
      "attributes": {
        "name": "cache-control",
        "content": "max-age=0, private, must-revalidate"
      }
    },
    {
      "type": "WebApplicationHeader",
      "attributes": {
        "name": "content-type",
        "content": "text/html; charset=utf-8"
      }
    },
    {
      "type": "WebApplicationHeader",
      "attributes": {
        "name": "access-control-allow-credentials",
        "content": "true"
      }
    },
    {
      "type": "WebApplicationHeader",
      "attributes": {
        "name": "status",
        "content": "200 OK"
      }
    },
    {
      "type": "WebApplicationHeader",
      "attributes": {
        "name": "x-request-id",
        "content": "a68c5746-b317-4fce-b7d9-72049dfb4829"
      }
    },
    {
      "type": "WebApplicationHeader",
      "attributes": {
        "name": "x-revision",
        "content": "446dcad5f249b8d1831b6c2fc783546d0fb713f8"
      }
    },
    {
      "type": "WebApplicationHeader",
      "attributes": {
        "name": "x-xss-protection",
        "content": "1; mode=block"
      }
    },
    {
      "type": "WebApplicationHeader",
      "attributes": {
        "name": "transfer-encoding",
        "content": "chunked"
      }
    },
    {
      "type": "WebApplicationHeader",
      "attributes": {
        "name": "x-runtime",
        "content": "0.299612"
      }
    },
    {
      "type": "WebApplicationHeader",
      "attributes": {
        "name": "access-control-allow-origin",
        "content": "http://reverb.com"
      }
    },
    {
      "type": "WebApplicationHeader",
      "attributes": {
        "name": "x-content-type-options",
        "content": "nosniff"
      }
    },
    {
      "type": "WebApplicationHeader",
      "attributes": {
        "name": "etag",
        "content": "W/\"b61e53d3d28083afef0e786322892182\""
      }
    },
    {
      "type": "WebApplicationHeader",
      "attributes": {
        "name": "connection",
        "content": "keep-alive"
      }
    },
    {
      "type": "WebApplicationHeader",
      "attributes": {
        "name": "set-cookie",
        "content": "X-Mapping-fjhppofk=56C1618A3C53D264CB0AF7460628DC15; path=/, return_to=https%3A%2F%2Freverb.com%2F; path=/, split=%7B%22onboarding_banner_ab_test%3A3%22%3A%22cable_banner%22%7D; path=/; expires=Fri, 22 Jan 2016 19:45:08 -0000, _reverb_session=BAh7B0kiD3Nlc3Npb25faWQGOgZFVEkiJTk5NDczNDI0YjgxMzRhNWE4MGRmNTcwMTljZjZmZTkyBjsAVEkiEF9jc3JmX3Rva2VuBjsARkkiMTlnY2VXZnNBbENtdUprdnhsaWYweE8rcUN0WGFxeVlrMU9BWjgySU8zNlU9BjsARg%3D%3D--b84597c115d6dac82adbbbb85eaedc3ad055fff6; path=/; HttpOnly"
      }
    },
    {
      "type": "WebApplicationHeader",
      "attributes": {
        "name": "x-frame-options",
        "content": "SAMEORIGIN"
      }
    }
  ]
}