{
  "task_name": "web_app_gather_headers",
  "entity": {
    "type": "WebApplication",
    "attributes": {
      "name": "http://soundhouse.co.jp"
    }
  },
  "entities": [
    {
      "type": "WebApplicationHeader",
      "attributes": {
        "name": "content-type",
        "content": "text/html; charset=UTF-8"
      }
    },
    {
      "type": "WebApplicationHeader",
      "attributes": {
        "name": "transfer-encoding",
        "content": "chunked"
      }
    },
    {
      "type": "WebApplicationHeader",
      "attributes": {
        "name": "vary",
        "content": "Accept-Encoding"
      }
    },
    {
      "type": "WebApplicationHeader",
      "attributes": {
        "name": "set-cookie",
        "content": "ENC_sh_sess=VNENPMvuV%2bIwXg4wZUYq0Ipf3Vc4a/ydjvFnqNYv9NV6cTufgJG90Ih%2bL6zByH%2bc; expires=Sat, 17-Jan-2015 14:29:01 GMT; Max-Age=86400; path=/; HttpOnly, ENC_ua=CaWhxhqsCxAvUQs50bgDAA%3d%3d; expires=Thu, 01-Jan-1970 00:00:01 GMT; Max-Age=0; secure; httponly; HttpOnly, BIGipServerPHP_80=c0rg23IV7jHWIJMTKlGGEO4HOx+BNEAJfdFhjhhGiRDdyU6f7bd9F8/oBDW6c6w/ZGd4ecju/jsHmg==; path=/"
      }
    },
    {
      "type": "WebApplicationHeader",
      "attributes": {
        "name": "cache-control",
        "content": "no-store, no-cache, must-revalidate, post-check=0, pre-check=0"
      }
    },
    {
      "type": "WebApplicationHeader",
      "attributes": {
        "name": "pragma",
        "content": "no-cache"
      }
    },
    {
      "type": "WebApplicationHeader",
      "attributes": {
        "name": "connection",
        "content": "Keep-Alive"
      }
    }
  ]
}