{
  "task_name": "web_app_gather_headers",
  "entity": {
    "type": "WebApplication",
    "attributes": {
      "name": "http://tass.ru"
    }
  },
  "entities": [
    {
      "type": "WebApplicationHeader",
      "attributes": {
        "name": "server",
        "content": "QRATOR"
      }
    },
    {
      "type": "WebApplicationHeader",
      "attributes": {
        "name": "content-type",
        "content": "text/html; charset=UTF-8"
      }
    },
    {
      "type": "WebApplicationHeader",
      "attributes": {
        "name": "transfer-encoding",
        "content": "chunked"
      }
    },
    {
      "type": "WebApplicationHeader",
      "attributes": {
        "name": "connection",
        "content": "keep-alive"
      }
    },
    {
      "type": "WebApplicationHeader",
      "attributes": {
        "name": "keep-alive",
        "content": "timeout=15"
      }
    },
    {
      "type": "WebApplicationHeader",
      "attributes": {
        "name": "set-cookie",
        "content": "route=076ffc920dfc88fc3b9c405cf3e3b690; Expires=Sun, 11-Jan-2015 07:56:51 GMT; Path=/, geo_country_code=RU; expires=Sun, 13-Dec-2015 06:56:51 GMT; path=/, geo_city_id=2097; expires=Sun, 13-Dec-2015 06:56:51 GMT; path=/, geo_ip_hash=136b067565602858485b73e350111238; expires=Sun, 13-Dec-2015 06:56:51 GMT; path=/, geo_region_id=42; expires=Sun, 13-Dec-2015 06:56:51 GMT; path=/, PHPSESSID=tdvs359i5le37d3galrci09tp3; expires=Mon, 11-Jan-2016 06:56:51 GMT; path=/; HttpOnly, YII_CSRF_TOKEN=6a749f3d6261d5fc4f68fe7991be9206f5cb00cb; path=/; httponly"
      }
    },
    {
      "type": "WebApplicationHeader",
      "attributes": {
        "name": "cache-control",
        "content": "no-store, no-cache, must-revalidate, post-check=0, pre-check=0"
      }
    },
    {
      "type": "WebApplicationHeader",
      "attributes": {
        "name": "pragma",
        "content": "no-cache"
      }
    }
  ]
}