{
  "task_name": "web_app_gather_headers",
  "entity": {
    "type": "WebApplication",
    "attributes": {
      "name": "http://the-village.ru"
    }
  },
  "entities": [
    {
      "type": "WebApplicationHeader",
      "attributes": {
        "name": "server",
        "content": "nginx"
      }
    },
    {
      "type": "WebApplicationHeader",
      "attributes": {
        "name": "content-type",
        "content": "text/html; charset=utf-8"
      }
    },
    {
      "type": "WebApplicationHeader",
      "attributes": {
        "name": "transfer-encoding",
        "content": "chunked"
      }
    },
    {
      "type": "WebApplicationHeader",
      "attributes": {
        "name": "connection",
        "content": "keep-alive"
      }
    },
    {
      "type": "WebApplicationHeader",
      "attributes": {
        "name": "status",
        "content": "200 OK"
      }
    },
    {
      "type": "WebApplicationHeader",
      "attributes": {
        "name": "etag",
        "content": "\"27d6ad98aa891ae7def1b38502afc785\""
      }
    },
    {
      "type": "WebApplicationHeader",
      "attributes": {
        "name": "cache-control",
        "content": "max-age=0, private, must-revalidate"
      }
    },
    {
      "type": "WebApplicationHeader",
      "attributes": {
        "name": "set-cookie",
        "content": "city_id=1; path=/; expires=Sat, 11-Apr-2015 16:59:43 GMT, lam=BAh7B0kiD3Nlc3Npb25faWQGOgZFRkkiJWE2YTUwOTUzYTUzN2M3M2RhMWFjMWY0OWNhMTdiNmUxBjsAVEkiEF9jc3JmX3Rva2VuBjsARkkiMU9UUXpBSG5rT2k3NFhmVEQ2ajg0aDdzeUdBaHZCVGFiZWc1Qk9KUE5EdHc9BjsARg%3D%3D--eb588c18e9ed7688d7a299a6c8c6e8852dc5b400; domain=.the-village.ru; path=/; expires=Sun, 25-Jan-2015 16:59:43 GMT"
      }
    },
    {
      "type": "WebApplicationHeader",
      "attributes": {
        "name": "x-runtime",
        "content": "0.114348"
      }
    }
  ]
}