{
  "task_name": "web_app_gather_headers",
  "entity": {
    "type": "WebApplication",
    "attributes": {
      "name": "http://turbosquid.com"
    }
  },
  "entities": [
    {
      "type": "WebApplicationHeader",
      "attributes": {
        "name": "content-type",
        "content": "text/html; charset=UTF-8"
      }
    },
    {
      "type": "WebApplicationHeader",
      "attributes": {
        "name": "server",
        "content": "Microsoft-IIS/7.5"
      }
    },
    {
      "type": "WebApplicationHeader",
      "attributes": {
        "name": "set-cookie",
        "content": "enable_beta=1;path=/;expires=Fri, 19 Feb 2016 15:45:58 GMT;, M=4a1f60c9%2D48cf%2D4f04%2D97f8%2Dadccf67b6bf3;domain=.turbosquid.com;expires=Sat, 11-Feb-2045 15:45:59 GMT;path=/, M20UR15=s%3DE02625A1%2D1E15%2D4901%2D8F74%2D634738F893BD;domain=.www.turbosquid.com;expires=Sat, 21-Mar-2015 15:45:59 GMT;path=/, SERVERID=; Expires=Thu, 01-Jan-1970 00:00:01 GMT; path=/"
      }
    },
    {
      "type": "WebApplicationHeader",
      "attributes": {
        "name": "x-powered-by",
        "content": "ASP.NET"
      }
    },
    {
      "type": "WebApplicationHeader",
      "attributes": {
        "name": "connection",
        "content": "close"
      }
    },
    {
      "type": "WebApplicationHeader",
      "attributes": {
        "name": "cache-control",
        "content": "private"
      }
    }
  ]
}