{
  "task_name": "web_app_gather_headers",
  "entity": {
    "type": "WebApplication",
    "attributes": {
      "name": "http://tvb.com"
    }
  },
  "entities": [
    {
      "type": "WebApplicationHeader",
      "attributes": {
        "name": "server",
        "content": "Apache/2"
      }
    },
    {
      "type": "WebApplicationHeader",
      "attributes": {
        "name": "x-powered-by",
        "content": "PHP/5.3.21"
      }
    },
    {
      "type": "WebApplicationHeader",
      "attributes": {
        "name": "set-cookie",
        "content": "fbss_o=nNr32toha3X8DZCD68X1JNRZ0DRqG6ygW9wn4blA7Ks.eyJkb21haW4iOiJ0dmIuY29tIiwiaWQiOiIwMjcwMzRiMWZiMzkyMjFkMmQwNjI4MzQ2NjA2ZjI3YyIsImFsZ29yaXRobSI6IkhNQUMtU0hBMjU2IiwiaXNzdWVkX2F0IjoxNDIyMDcyMTQ2fQ; expires=Sun, 24-Jan-2016 09:51:12 GMT; path=/; domain=.tvb.com"
      }
    },
    {
      "type": "WebApplicationHeader",
      "attributes": {
        "name": "vary",
        "content": "Accept-Encoding"
      }
    },
    {
      "type": "WebApplicationHeader",
      "attributes": {
        "name": "connection",
        "content": "close"
      }
    },
    {
      "type": "WebApplicationHeader",
      "attributes": {
        "name": "content-type",
        "content": "text/html"
      }
    }
  ]
}